labelme_parse/__init__.py
labelme_parse/generator.py
labelme_parse/labels.py
labelme_parse/py.typed
labelme_parse-1.0.9.dist-info/LICENSE
labelme_parse-1.0.9.dist-info/METADATA
labelme_parse-1.0.9.dist-info/WHEEL
labelme_parse-1.0.9.dist-info/top_level.txt
labelme_parse-1.0.9.dist-info/RECORD
