Metadata-Version: 2.1
Name: labelme-parse
Version: 1.0.9
Summary: Utility functions to parse json file generated by labelme
Author-email: Pradish Bijukchhe <pradish@sandbox.com.np>
License: Copyright (c) 2018 The Python Packaging Authority
Project-URL: Homepage, https://github.com/sandbox-pokhara/labelme-parse
Project-URL: Issues, https://github.com/sandbox-pokhara/labelme-parse/issues
Classifier: Programming Language :: Python :: 3
Requires-Python: >=3
License-File: LICENSE
